omniblack/model/IdDict.py
omniblack/model/__init__.py
omniblack/model/_repl.py
omniblack/model/abc.py
omniblack/model/coercion.py
omniblack/model/dot_path.py
omniblack/model/errors.py
omniblack/model/field.py
omniblack/model/format.py
omniblack/model/format_classes.py
omniblack/model/format_registry.py
omniblack/model/json_schema.py
omniblack/model/localization.py
omniblack/model/mapper.py
omniblack/model/metadata.py
omniblack/model/plugin.py
omniblack/model/preprocess_struct.py
omniblack/model/slots.py
omniblack/model/storage.py
omniblack/model/struct.py
omniblack/model/type_registry.py
omniblack/model/undefined.py
omniblack/model/validationResult.py
omniblack/model/walker.py
omniblack/model/formats/__init__.py
omniblack/model/formats/toml.py
omniblack/model/meta_model/__init__.py
omniblack/model/meta_model/attr_field.json
omniblack/model/meta_model/choice_member.json
omniblack/model/meta_model/field.json
omniblack/model/meta_model/struct.json
omniblack/model/meta_model/ui_string.json
omniblack/model/model/__init__.py
omniblack/model/test_model/__init__.py
omniblack/model/test_model/adventurer.toml
omniblack/model/types/__init__.py
omniblack/model/types/any.py
omniblack/model/types/binary.py
omniblack/model/types/boolean.py
omniblack/model/types/child.py
omniblack/model/types/choice.py
omniblack/model/types/date.py
omniblack/model/types/datetime.py
omniblack/model/types/email.py
omniblack/model/types/estimate.py
omniblack/model/types/integer.py
omniblack/model/types/list_attrs.json
omniblack/model/types/path.py
omniblack/model/types/string.py
omniblack.model-0.1.19.dist-info/LICENSE.txt
omniblack.model-0.1.19.dist-info/METADATA
omniblack.model-0.1.19.dist-info/WHEEL
omniblack.model-0.1.19.dist-info/top_level.txt
omniblack.model-0.1.19.dist-info/RECORD
