Metadata-Version: 2.1
Name: omniblack.model
Version: 0.1.19
Summary: A library enabling model driven development.
Author-email: Terry Patterson <Terryp@wegrok.net>
License: 
Project-URL: Homepage, https://gitlab.com/terryp/terry/-/tree/next/model/py
Project-URL: Repository, https://gitlab.com/terryp/terry.git
Requires-Python: ~=3.9
License-File: LICENSE.txt
Requires-Dist: more-itertools ~=10.0
Requires-Dist: humanize ~=3.4
Requires-Dist: toml ~=0.10
Requires-Dist: atpublic ~=4.0
Requires-Dist: pluggy ~=1.3.0
Provides-Extra: yaml
Requires-Dist: ruamel.yaml ~=0.16 ; extra == 'yaml'
